[{"player":{"name":"Bijan Robinson","sleeperId":"9509","position":"RB"},"redraftValue":10415},{"player":{"name":"Jahmyr Gibbs","sleeperId":"9221","position":"RB"},"redraftValue":10364},{"player":{"name":"Ja'Marr Chase","sleeperId":"7564","position":"WR"},"redraftValue":10006},{"player":{"name":"Jonathan Taylor","sleeperId":"6813","position":"RB"},"redraftValue":8718},{"player":{"name":"Jaxon Smith-Njigba","sleeperId":"9488","position":"WR"},"redraftValue":8903},{"player":{"name":"Puka Nacua","sleeperId":"9493","position":"WR"},"redraftValue":8809},{"player":{"name":"Amon-Ra St. Brown","sleeperId":"7547","position":"WR"},"redraftValue":8603},{"player":{"name":"Justin Jefferson","sleeperId":"6794","position":"WR"},"redraftValue":8414},{"player":{"name":"Ashton Jeanty","sleeperId":"12527","position":"RB"},"redraftValue":8082},{"player":{"name":"James Cook","sleeperId":"8138","position":"RB"},"redraftValue":7904},{"player":{"name":"De'Von Achane","sleeperId":"9226","position":"RB"},"redraftValue":7868},{"player":{"name":"Christian McCaffrey","sleeperId":"4034","position":"RB"},"redraftValue":7862},{"player":{"name":"CeeDee Lamb","sleeperId":"6786","position":"WR"},"redraftValue":7855},{"player":{"name":"Omarion Hampton","sleeperId":"12507","position":"RB"},"redraftValue":7256},{"player":{"name":"Saquon Barkley","sleeperId":"4866","position":"RB"},"redraftValue":7195},{"player":{"name":"Jeremiyah Love","sleeperId":"13287","position":"RB"},"redraftValue":6736},{"player":{"name":"Trey McBride","sleeperId":"8130","position":"TE"},"redraftValue":6971},{"player":{"name":"Derrick Henry","sleeperId":"3198","position":"RB"},"redraftValue":6410},{"player":{"name":"Brock Bowers","sleeperId":"11604","position":"TE"},"redraftValue":6385},{"player":{"name":"Drake London","sleeperId":"8112","position":"WR"},"redraftValue":6105},{"player":{"name":"Kenneth Walker","sleeperId":"8151","position":"RB"},"redraftValue":5903},{"player":{"name":"Chase Brown","sleeperId":"9224","position":"RB"},"redraftValue":5766},{"player":{"name":"Josh Allen","sleeperId":"4984","position":"QB"},"redraftValue":6099},{"player":{"name":"Malik Nabers","sleeperId":"11632","position":"WR"},"redraftValue":5621},{"player":{"name":"Breece Hall","sleeperId":"8155","position":"RB"},"redraftValue":5165},{"player":{"name":"Kyren Williams","sleeperId":"8150","position":"RB"},"redraftValue":4971},{"player":{"name":"A.J. Brown","sleeperId":"5859","position":"WR"},"redraftValue":4921},{"player":{"name":"Nico Collins","sleeperId":"7569","position":"WR"},"redraftValue":4865},{"player":{"name":"TreVeyon Henderson","sleeperId":"12529","position":"RB"},"redraftValue":4632},{"player":{"name":"George Pickens","sleeperId":"8137","position":"WR"},"redraftValue":4622},{"player":{"name":"Javonte Williams","sleeperId":"7588","position":"RB"},"redraftValue":4319},{"player":{"name":"Quinshon Judkins","sleeperId":"12512","position":"RB"},"redraftValue":4262},{"player":{"name":"Travis Etienne","sleeperId":"7543","position":"RB"},"redraftValue":4249},{"player":{"name":"Josh Jacobs","sleeperId":"5850","position":"RB"},"redraftValue":4249},{"player":{"name":"Garrett Wilson","sleeperId":"8146","position":"WR"},"redraftValue":4301},{"player":{"name":"Tetairoa McMillan","sleeperId":"12526","position":"WR"},"redraftValue":4010},{"player":{"name":"Cam Skattebo","sleeperId":"12481","position":"RB"},"redraftValue":3750},{"player":{"name":"Chris Olave","sleeperId":"8144","position":"WR"},"redraftValue":3580},{"player":{"name":"DeVonta Smith","sleeperId":"7525","position":"WR"},"redraftValue":3531},{"player":{"name":"Emeka Egbuka","sleeperId":"12514","position":"WR"},"redraftValue":3473},{"player":{"name":"Tee Higgins","sleeperId":"6801","position":"WR"},"redraftValue":3420},{"player":{"name":"Bucky Irving","sleeperId":"11584","position":"RB"},"redraftValue":3329},{"player":{"name":"David Montgomery","sleeperId":"5892","position":"RB"},"redraftValue":3277},{"player":{"name":"Lamar Jackson","sleeperId":"4881","position":"QB"},"redraftValue":3452},{"player":{"name":"Rashee Rice","sleeperId":"10229","position":"WR"},"redraftValue":3263},{"player":{"name":"Drake Maye","sleeperId":"11564","position":"QB"},"redraftValue":3325},{"player":{"name":"Ladd McConkey","sleeperId":"11635","position":"WR"},"redraftValue":3120},{"player":{"name":"Jaylen Waddle","sleeperId":"7526","position":"WR"},"redraftValue":3117},{"player":{"name":"Joe Burrow","sleeperId":"6770","position":"QB"},"redraftValue":3239},{"player":{"name":"Jadarian Price","sleeperId":"13286","position":"RB"},"redraftValue":2911},{"player":{"name":"Tyler Warren","sleeperId":"12518","position":"TE"},"redraftValue":2911},{"player":{"name":"D'Andre Swift","sleeperId":"6790","position":"RB"},"redraftValue":2717},{"player":{"name":"Zay Flowers","sleeperId":"9997","position":"WR"},"redraftValue":2745},{"player":{"name":"Colston Loveland","sleeperId":"12517","position":"TE"},"redraftValue":2722},{"player":{"name":"Jayden Daniels","sleeperId":"11566","position":"QB"},"redraftValue":2636},{"player":{"name":"Davante Adams","sleeperId":"2133","position":"WR"},"redraftValue":2414},{"player":{"name":"Patrick Mahomes","sleeperId":"4046","position":"QB"},"redraftValue":2492},{"player":{"name":"Caleb Williams","sleeperId":"11560","position":"QB"},"redraftValue":2487},{"player":{"name":"Mike Evans","sleeperId":"2216","position":"WR"},"redraftValue":2343},{"player":{"name":"Carnell Tate","sleeperId":"13279","position":"WR"},"redraftValue":2317},{"player":{"name":"Rome Odunze","sleeperId":"11620","position":"WR"},"redraftValue":2176},{"player":{"name":"Justin Herbert","sleeperId":"6797","position":"QB"},"redraftValue":2223},{"player":{"name":"Tucker Kraft","sleeperId":"9484","position":"TE"},"redraftValue":2126},{"player":{"name":"Marvin Harrison Jr","sleeperId":"11628","position":"WR"},"redraftValue":2095},{"player":{"name":"Terry McLaurin","sleeperId":"5927","position":"WR"},"redraftValue":1962},{"player":{"name":"Jaylen Warren","sleeperId":"8228","position":"RB"},"redraftValue":1823},{"player":{"name":"Brian Thomas","sleeperId":"11631","position":"WR"},"redraftValue":1849},{"player":{"name":"Chuba Hubbard","sleeperId":"7594","position":"RB"},"redraftValue":1787},{"player":{"name":"Jameson Williams","sleeperId":"8148","position":"WR"},"redraftValue":1804},{"player":{"name":"Luther Burden","sleeperId":"12519","position":"WR"},"redraftValue":1724},{"player":{"name":"Jalen Hurts","sleeperId":"6904","position":"QB"},"redraftValue":1763},{"player":{"name":"Bhayshul Tuten","sleeperId":"12490","position":"RB"},"redraftValue":1517},{"player":{"name":"George Kittle","sleeperId":"4217","position":"TE"},"redraftValue":1568},{"player":{"name":"DJ Moore","sleeperId":"4983","position":"WR"},"redraftValue":1539},{"player":{"name":"Tony Pollard","sleeperId":"5967","position":"RB"},"redraftValue":1463},{"player":{"name":"Jordyn Tyson","sleeperId":"13281","position":"WR"},"redraftValue":1499},{"player":{"name":"Sam LaPorta","sleeperId":"10859","position":"TE"},"redraftValue":1361},{"player":{"name":"Kyle Pitts","sleeperId":"7553","position":"TE"},"redraftValue":1352},{"player":{"name":"Rico Dowdle","sleeperId":"7021","position":"RB"},"redraftValue":1287},{"player":{"name":"Makai Lemon","sleeperId":"13294","position":"WR"},"redraftValue":1292},{"player":{"name":"RJ Harvey","sleeperId":"12489","position":"RB"},"redraftValue":1259},{"player":{"name":"Dak Prescott","sleeperId":"3294","position":"QB"},"redraftValue":1311},{"player":{"name":"Rhamondre Stevenson","sleeperId":"7611","position":"RB"},"redraftValue":1223},{"player":{"name":"Travis Kelce","sleeperId":"1466","position":"TE"},"redraftValue":1263},{"player":{"name":"Aaron Jones","sleeperId":"4199","position":"RB"},"redraftValue":1193},{"player":{"name":"Trevor Lawrence","sleeperId":"7523","position":"QB"},"redraftValue":1259},{"player":{"name":"Kenneth Gainwell","sleeperId":"7567","position":"RB"},"redraftValue":1157},{"player":{"name":"J.K. Dobbins","sleeperId":"6806","position":"RB"},"redraftValue":1132},{"player":{"name":"Christian Watson","sleeperId":"8167","position":"WR"},"redraftValue":1123},{"player":{"name":"Rachaad White","sleeperId":"8136","position":"RB"},"redraftValue":1095},{"player":{"name":"Alec Pierce","sleeperId":"8142","position":"WR"},"redraftValue":1028},{"player":{"name":"Michael Pittman","sleeperId":"6819","position":"WR"},"redraftValue":1023},{"player":{"name":"DK Metcalf","sleeperId":"5846","position":"WR"},"redraftValue":1018},{"player":{"name":"Kyle Monangai","sleeperId":"12534","position":"RB"},"redraftValue":937},{"player":{"name":"Courtland Sutton","sleeperId":"5045","position":"WR"},"redraftValue":939},{"player":{"name":"Blake Corum","sleeperId":"11586","position":"RB"},"redraftValue":909},{"player":{"name":"Zach Charbonnet","sleeperId":"9753","position":"RB"},"redraftValue":861},{"player":{"name":"Bo Nix","sleeperId":"11563","position":"QB"},"redraftValue":902},{"player":{"name":"Jaxson Dart","sleeperId":"12508","position":"QB"},"redraftValue":876},{"player":{"name":"Alvin Kamara","sleeperId":"4035","position":"RB"},"redraftValue":779},{"player":{"name":"Jonah Coleman","sleeperId":"13345","position":"RB"},"redraftValue":759},{"player":{"name":"Brock Purdy","sleeperId":"8183","position":"QB"},"redraftValue":805},{"player":{"name":"Mark Andrews","sleeperId":"5012","position":"TE"},"redraftValue":747},{"player":{"name":"Jacory Croskey-Merritt","sleeperId":"12533","position":"RB"},"redraftValue":686},{"player":{"name":"Michael Wilson","sleeperId":"10232","position":"WR"},"redraftValue":661},{"player":{"name":"Chris Godwin","sleeperId":"4037","position":"WR"},"redraftValue":620},{"player":{"name":"KC Concepcion","sleeperId":"13298","position":"WR"},"redraftValue":617},{"player":{"name":"Tyrone Tracy","sleeperId":"11655","position":"RB"},"redraftValue":601},{"player":{"name":"Jakobi Meyers","sleeperId":"5947","position":"WR"},"redraftValue":605},{"player":{"name":"Harold Fannin","sleeperId":"12506","position":"TE"},"redraftValue":611},{"player":{"name":"Jordan Love","sleeperId":"6804","position":"QB"},"redraftValue":624},{"player":{"name":"Jordan Mason","sleeperId":"8408","position":"RB"},"redraftValue":566},{"player":{"name":"Stefon Diggs","sleeperId":"2449","position":"WR"},"redraftValue":573},{"player":{"name":"Jared Goff","sleeperId":"3163","position":"QB"},"redraftValue":597},{"player":{"name":"Jake Ferguson","sleeperId":"8110","position":"TE"},"redraftValue":563},{"player":{"name":"Ricky Pearsall","sleeperId":"11638","position":"WR"},"redraftValue":553},{"player":{"name":"Jordan Addison","sleeperId":"9756","position":"WR"},"redraftValue":531},{"player":{"name":"Jonathon Brooks","sleeperId":"11583","position":"RB"},"redraftValue":505},{"player":{"name":"Isiah Pacheco","sleeperId":"8205","position":"RB"},"redraftValue":504},{"player":{"name":"Tyler Allgeier","sleeperId":"8132","position":"RB"},"redraftValue":497},{"player":{"name":"Matthew Stafford","sleeperId":"421","position":"QB"},"redraftValue":514},{"player":{"name":"Wan'Dale Robinson","sleeperId":"8126","position":"WR"},"redraftValue":490},{"player":{"name":"Quentin Johnston","sleeperId":"9754","position":"WR"},"redraftValue":484},{"player":{"name":"Jayden Reed","sleeperId":"10222","position":"WR"},"redraftValue":477},{"player":{"name":"Brian Robinson","sleeperId":"8154","position":"RB"},"redraftValue":438},{"player":{"name":"Parker Washington","sleeperId":"9487","position":"WR"},"redraftValue":417},{"player":{"name":"Omar Cooper","sleeperId":"13276","position":"WR"},"redraftValue":405},{"player":{"name":"Chris Rodriguez","sleeperId":"10219","position":"RB"},"redraftValue":360},{"player":{"name":"Dalton Kincaid","sleeperId":"10236","position":"TE"},"redraftValue":372},{"player":{"name":"Nicholas Singleton","sleeperId":"13288","position":"RB"},"redraftValue":350},{"player":{"name":"Josh Downs","sleeperId":"9500","position":"WR"},"redraftValue":341},{"player":{"name":"Woody Marks","sleeperId":"12474","position":"RB"},"redraftValue":327},{"player":{"name":"Denzel Boston","sleeperId":"13346","position":"WR"},"redraftValue":322},{"player":{"name":"Baker Mayfield","sleeperId":"4892","position":"QB"},"redraftValue":327},{"player":{"name":"Isaiah Likely","sleeperId":"8131","position":"TE"},"redraftValue":280},{"player":{"name":"Cam Ward","sleeperId":"12522","position":"QB"},"redraftValue":280},{"player":{"name":"Dallas Goedert","sleeperId":"5022","position":"TE"},"redraftValue":251},{"player":{"name":"Kenyon Sadiq","sleeperId":"13330","position":"TE"},"redraftValue":248},{"player":{"name":"Jayden Higgins","sleeperId":"12484","position":"WR"},"redraftValue":234},{"player":{"name":"Eli Stowers","sleeperId":"13349","position":"TE"},"redraftValue":232},{"player":{"name":"Matthew Golden","sleeperId":"12501","position":"WR"},"redraftValue":225},{"player":{"name":"Travis Hunter","sleeperId":"12530","position":"WR"},"redraftValue":225},{"player":{"name":"Romeo Doubs","sleeperId":"8121","position":"WR"},"redraftValue":224},{"player":{"name":"Brandon Aiyuk","sleeperId":"6803","position":"WR"},"redraftValue":220},{"player":{"name":"Fernando Mendoza","sleeperId":"13269","position":"QB"},"redraftValue":227},{"player":{"name":"Tyreek Hill","sleeperId":"3321","position":"WR"},"redraftValue":209},{"player":{"name":"Rashid Shaheed","sleeperId":"8676","position":"WR"},"redraftValue":203},{"player":{"name":"T.J. Hockenson","sleeperId":"5844","position":"TE"},"redraftValue":193},{"player":{"name":"Tyler Shough","sleeperId":"12545","position":"QB"},"redraftValue":195},{"player":{"name":"Tank Bigsby","sleeperId":"9225","position":"RB"},"redraftValue":170},{"player":{"name":"Xavier Worthy","sleeperId":"11624","position":"WR"},"redraftValue":173},{"player":{"name":"Keaton Mitchell","sleeperId":"9511","position":"RB"},"redraftValue":160},{"player":{"name":"Kyler Murray","sleeperId":"5849","position":"QB"},"redraftValue":167},{"player":{"name":"Khalil Shakir","sleeperId":"8134","position":"WR"},"redraftValue":159},{"player":{"name":"C.J. Stroud","sleeperId":"9758","position":"QB"},"redraftValue":163},{"player":{"name":"Sam Darnold","sleeperId":"4943","position":"QB"},"redraftValue":158},{"player":{"name":"Hunter Henry","sleeperId":"3214","position":"TE"},"redraftValue":130},{"player":{"name":"MarShawn Lloyd","sleeperId":"11581","position":"RB"},"redraftValue":124},{"player":{"name":"Juwan Johnson","sleeperId":"7002","position":"TE"},"redraftValue":124},{"player":{"name":"Tyjae Spears","sleeperId":"9508","position":"RB"},"redraftValue":117},{"player":{"name":"Jalen Coker","sleeperId":"11646","position":"WR"},"redraftValue":118},{"player":{"name":"Chig Okonkwo","sleeperId":"8210","position":"TE"},"redraftValue":114},{"player":{"name":"Emmett Johnson","sleeperId":"13337","position":"RB"},"redraftValue":106},{"player":{"name":"Dalton Schultz","sleeperId":"5001","position":"TE"},"redraftValue":110},{"player":{"name":"Oronde Gadsden","sleeperId":"12493","position":"TE"},"redraftValue":110},{"player":{"name":"Jauan Jennings","sleeperId":"7049","position":"WR"},"redraftValue":106},{"player":{"name":"Brenton Strange","sleeperId":"9480","position":"TE"},"redraftValue":102},{"player":{"name":"Dylan Sampson","sleeperId":"12469","position":"RB"},"redraftValue":89},{"player":{"name":"Jalen McMillan","sleeperId":"11618","position":"WR"},"redraftValue":89},{"player":{"name":"Jalen Nailor","sleeperId":"8180","position":"WR"},"redraftValue":86},{"player":{"name":"Kaytron Allen","sleeperId":"13405","position":"RB"},"redraftValue":67},{"player":{"name":"Jerry Jeudy","sleeperId":"6783","position":"WR"},"redraftValue":62},{"player":{"name":"Tank Dell","sleeperId":"9502","position":"WR"},"redraftValue":59},{"player":{"name":"David Njoku","sleeperId":"4033","position":"TE"},"redraftValue":59},{"player":{"name":"Chris Bell","sleeperId":"13311","position":"WR"},"redraftValue":56},{"player":{"name":"De'Zhaun Stribling","sleeperId":"13417","position":"WR"},"redraftValue":55},{"player":{"name":"Kaelon Black","sleeperId":"13414","position":"RB"},"redraftValue":52},{"player":{"name":"Antonio Williams","sleeperId":"13301","position":"WR"},"redraftValue":52},{"player":{"name":"Daniel Jones","sleeperId":"5870","position":"QB"},"redraftValue":53},{"player":{"name":"Braelon Allen","sleeperId":"11576","position":"RB"},"redraftValue":43},{"player":{"name":"Kaleb Johnson","sleeperId":"12504","position":"RB"},"redraftValue":39},{"player":{"name":"Germie Bernard","sleeperId":"13274","position":"WR"},"redraftValue":37},{"player":{"name":"Tre' Harris","sleeperId":"12509","position":"WR"},"redraftValue":37},{"player":{"name":"AJ Barner","sleeperId":"11603","position":"TE"},"redraftValue":31},{"player":{"name":"Bryce Young","sleeperId":"9228","position":"QB"},"redraftValue":32},{"player":{"name":"Deebo Samuel","sleeperId":"5872","position":"WR"},"redraftValue":28},{"player":{"name":"Mike Washington","sleeperId":"13305","position":"RB"},"redraftValue":26},{"player":{"name":"Kimani Vidal","sleeperId":"11647","position":"RB"},"redraftValue":22},{"player":{"name":"Malik Willis","sleeperId":"8161","position":"QB"},"redraftValue":21},{"player":{"name":"Emanuel Wilson","sleeperId":"11435","position":"RB"},"redraftValue":10},{"player":{"name":"Elijah Sarratt","sleeperId":"13268","position":"WR"},"redraftValue":6},{"player":{"name":"Aaron Rodgers","sleeperId":"96","position":"QB"},"redraftValue":6},{"player":{"name":"Malik Washington","sleeperId":"11610","position":"WR"},"redraftValue":5},{"player":{"name":"Trey Benson","sleeperId":"11589","position":"RB"},"redraftValue":3},{"player":{"name":"Adonai Mitchell","sleeperId":"11625","position":"WR"},"redraftValue":4},{"player":{"name":"Demond Claiborne","sleeperId":"13347","position":"RB"},"redraftValue":1},{"player":{"name":"Tre Tucker","sleeperId":"10213","position":"WR"},"redraftValue":2},{"player":{"name":"Calvin Ridley","sleeperId":"4981","position":"WR"},"redraftValue":2}]